setup.py
distributions_aws/Binomialdistribution.py
distributions_aws/Gaussiandistribution.py
distributions_aws/Generaldistribution.py
distributions_aws/__init__.py
distributions_aws.egg-info/PKG-INFO
distributions_aws.egg-info/SOURCES.txt
distributions_aws.egg-info/dependency_links.txt
distributions_aws.egg-info/not-zip-safe
distributions_aws.egg-info/top_level.txt