Metadata-Version: 1.0
Name: distributions-aws
Version: 0.1
Summary: Gaussian distributions
Home-page: UNKNOWN
Author: sameh abouelsaad
Author-email: UNKNOWN
License: UNKNOWN
Platform: UNKNOWN
